{"transcript":"bɛˈhânːdla","exists":true,"definitions":["Att hantera eller bearbeta något, ofta med avsikt att förändra eller förbättra det.","Att bemöta någon på ett visst sätt.","Att medicinskt vårda eller kurera en sjukdom eller skada."],"examples":["Läkaren behandlar patienten.","De behandlar ämnet i boken.","Man måste behandla djur väl."],"lemma":"behandla","lemmaPos":"verb","synonyms":["hantera","bearbeta","bemöta","vårda"],"number":"singular","pastTenses":"behandlade, har behandlat","tense":"present","source":"behandla"}