{"transcript":"틛fal틣b톝틟skri틣vn톩콂","exists":true,"definitions":["En detaljerad redog칬relse f칬r ett specifikt fall, ofta inom medicin, psykologi eller socialt arbete.","En beskrivning av en h칛ndelse eller situation som anv칛nds som exempel eller underlag f칬r analys."],"examples":["L칛karen presenterade en intressant fallbeskrivning.","Studenterna analyserade flera fallbeskrivningar.","En fallbeskrivning kan belysa komplexa problem."],"lemma":"fallbeskrivning","lemmaPos":"noun","synonyms":["fallstudie","exempelbeskrivning","kasuistik"],"number":"singular","pluralForm":"fallbeskrivningar","gender":"common","source":"fallbeskrivning"}