{"transcript":"²psyːkʊˌlɔɡ","exists":true,"definitions":["En person som har en akademisk examen i psykologi och arbetar med att studera och behandla mänskligt beteende och mentala processer.","Yrkesbeteckning för någon som utövar psykologi."],"examples":["Hon bestämde sig för att bli psykolog.","Psykologen lyssnade noga på patienten.","Många psykologer arbetar inom vården."],"lemma":"psykolog","lemmaPos":"noun","synonyms":["terapeut","kurator"],"number":"singular","pluralForm":"psykologer","gender":"common","source":"psykolog"}