{"transcript":"ˈlɔ̂kːa","exists":true,"definitions":["Att dra till sig, fängsla eller övertala någon eller något.","Att framkalla eller orsaka något, ofta positivt.","Att lura eller förleda någon till något."],"examples":["Fåglarna locka med sin sång.","Erbjudandet locka många sökande.","Hon locka fram ett leende hos honom."],"lemma":"locka","lemmaPos":"verb","synonyms":["attrahera","fresta","förleda","dra"],"number":"singular","tense":"present","pastTenses":"lockade (past simple), har lockat (present perfect)","source":"locka"}