{"transcript":"ˈɡrɪ̂lːa","exists":true,"definitions":["Att tillaga mat, särskilt kött eller grönsaker, över öppen eld eller på en grill.","Att utsätta någon för intensivt förhör eller kritik."],"examples":["Vi ska grilla korv ikväll.","Polisen började grilla den misstänkte.","Ska vi grilla lax till middag?","Journalisterna ville grilla politikern om skandalen."],"lemma":"grilla","lemmaPos":"verb","synonyms":["halstra","griljera","förhöra","kritisera"],"number":"singular","tense":"present","pastTenses":"grillade (past simple), har grillat (present perfect)","source":"grilla"}