{"transcript":"at ˈkɔmːa","exists":true,"definitions":["Röra sig från en plats till en annan, närmare talaren eller en viss punkt.","Anlända eller dyka upp.","Ske eller inträffa.","Bli eller utvecklas till något.","Följa med eller åtfölja."],"examples":["Han kommer hem sent ikväll.","När kommer bussen?","Det kommer att regna imorgon.","Hon kommer att bli en bra läkare.","Vill du komma med oss?"],"lemma":"komma","lemmaPos":"verb","synonyms":["anlända","dyka upp","inträffa","närma sig"],"number":"singular","pastTenses":"kom, har kommit","tense":"present","source":"att komma"}