{"transcript":"ﾋ坰ﾃｸﾌね甚etrﾉ嵶ね薪a","exists":true,"definitions":["Representera nﾃ･gon eller nﾃ･got.","Agera som ombud fﾃｶr nﾃ･gon.","Ha en viss stﾃ､llning eller position."],"examples":["Hon ska fﾃｶretrﾃ､da fﾃｶretaget pﾃ･ mﾃ､ssan.","Advokaten fﾃｶretrﾃ､der sin klient i rﾃ､tten.","Vem fﾃｶretrﾃ､der de anstﾃ､llda i styrelsen?"],"lemma":"fﾃｶretrﾃ､da","lemmaPos":"verb","synonyms":["representera","ombud","stﾃ･ fﾃｶr"],"number":"singular","tense":"present","pastTenses":"fﾃｶretrﾃ､dde, har fﾃｶretrﾃ､tt","source":"fﾃｶretrﾃ､da"}